cdef_cohort_generation/__init__.py
cdef_cohort_generation/__main__.py
cdef_cohort_generation/_version.py
cdef_cohort_generation/logging_config.py
cdef_cohort_generation/main.py
cdef_cohort_generation/population.py
cdef_cohort_generation/settings.py
cdef_cohort_generation/mappings/beskst13.json
cdef_cohort_generation/mappings/civst.json
cdef_cohort_generation/mappings/fm_mark.json
cdef_cohort_generation/mappings/hustype.json
cdef_cohort_generation/mappings/icd10.json
cdef_cohort_generation/mappings/isced.json
cdef_cohort_generation/mappings/jobkat.json
cdef_cohort_generation/mappings/plads.json
cdef_cohort_generation/mappings/pre_socio.json
cdef_cohort_generation/mappings/reg.json
cdef_cohort_generation/mappings/scd.json
cdef_cohort_generation/mappings/socio13.json
cdef_cohort_generation/mappings/statsb.json
cdef_cohort_generation/mappings/tilknyt.json
cdef_cohort_generation/registers/__init__.py
cdef_cohort_generation/registers/akm.py
cdef_cohort_generation/registers/bef.py
cdef_cohort_generation/registers/idan.py
cdef_cohort_generation/registers/ind.py
cdef_cohort_generation/registers/lpr3_diagnoser.py
cdef_cohort_generation/registers/lpr3_kontakter.py
cdef_cohort_generation/registers/lpr_adm.py
cdef_cohort_generation/registers/lpr_bes.py
cdef_cohort_generation/registers/lpr_diag.py
cdef_cohort_generation/registers/uddf.py
cdef_cohort_generation/utils/__init__.py
cdef_cohort_generation/utils/config.py
cdef_cohort_generation/utils/date.py
cdef_cohort_generation/utils/event.py
cdef_cohort_generation/utils/harmonize_lpr.py
cdef_cohort_generation/utils/hash_utils.py
cdef_cohort_generation/utils/icd.py
cdef_cohort_generation/utils/isced.py
cdef_cohort_generation/utils/mappings.py
cdef_cohort_generation/utils/register.py
cdef_cohort_generation/utils/types.py
cdef_cohort_generation-0.1.4.dist-info/METADATA
cdef_cohort_generation-0.1.4.dist-info/WHEEL
cdef_cohort_generation-0.1.4.dist-info/entry_points.txt
cdef_cohort_generation-0.1.4.dist-info/licenses/LICENSE.txt
cdef_cohort_generation-0.1.4.dist-info/RECORD
