Metadata-Version: 2.3
Name: cdef_cohort_generation
Version: 0.1.4
Summary: Add your description here
Project-URL: Source Code, https://github.com/LGS-Research-Group/cdef-cohort-generation/tree/d24e9e4a809726e9023eb9f2b593a2f0b15d3fa4
Author-email: Tobias Kragholm <50784887+tkragholm@users.noreply.github.com>
License-Expression: MIT
License-File: LICENSE.txt
Requires-Python: >=3.12
Requires-Dist: imohash>=1.1.0
Requires-Dist: polars[all]>=1.9.0
Requires-Dist: pydantic-settings>=2.5.2
Requires-Dist: pydantic[mypy]>=2.9.2
Requires-Dist: rich>=13.9.2
